j2_ioc/__init__.py
j2_ioc/_service_descriptor.py
j2_ioc/container.py
j2_ioc/lifetime.py
j2_ioc/scope.py
j2_ioc/errors/__init__.py
j2_ioc/errors/circular_dependency_error.py
j2_ioc/errors/container_error.py
j2_ioc/errors/missing_dependency_error.py
j2_ioc-1.0.6.dist-info/licenses/LICENSE
j2_ioc-1.0.6.dist-info/METADATA
j2_ioc-1.0.6.dist-info/WHEEL
j2_ioc-1.0.6.dist-info/top_level.txt
j2_ioc-1.0.6.dist-info/RECORD
