Metadata-Version: 2.4
Name: j2-ioc
Version: 1.0.6
Summary: A Python IoC (Inversion of Control) container
Author-email: J²-Consult ApS <info@j2-consult.dk>
License: MIT
Project-URL: Homepage, https://github.com/jeesondk/python-ioc-container/
Project-URL: Repository, https://github.com/jeesondk/python-ioc-container/
Project-URL: Bug Tracker, https://github.com/jeesondk/python-ioc-container/
Classifier: Development Status :: 3 - Alpha
Classifier: Intended Audience :: Developers
Classifier: License :: OSI Approved :: MIT License
Classifier: Programming Language :: Python :: 3.11
Classifier: Programming Language :: Python :: 3.12
Classifier: Programming Language :: Python :: 3.14
Requires-Python: >=3.8
License-File: LICENSE
Provides-Extra: dev
Requires-Dist: pytest>=7.4.0; extra == "dev"
Requires-Dist: pytest-cov>=4.1.0; extra == "dev"
Requires-Dist: black>=23.0.0; extra == "dev"
Requires-Dist: flake8>=6.0.0; extra == "dev"
Requires-Dist: mypy>=1.0.0; extra == "dev"
Requires-Dist: build>=1.0.0; extra == "dev"
Requires-Dist: twine>=4.0.0; extra == "dev"
Dynamic: license-file
